oduit/__init__.py
oduit/_version.py
oduit/addons_path_manager.py
oduit/base_process_manager.py
oduit/builders.py
oduit/cli_typer.py
oduit/cli_types.py
oduit/config_loader.py
oduit/config_provider.py
oduit/demo_process_manager.py
oduit/exceptions.py
oduit/manifest.py
oduit/manifest_collection.py
oduit/module_manager.py
oduit/odoo_code_executor.py
oduit/odoo_embedded_manager.py
oduit/odoo_operations.py
oduit/operation_result.py
oduit/output.py
oduit/process_manager.py
oduit/py.typed
oduit/utils.py
oduit-0.2.2.dist-info/licenses/AUTHORS
oduit-0.2.2.dist-info/licenses/LICENSE
oduit-0.2.2.dist-info/METADATA
oduit-0.2.2.dist-info/WHEEL
oduit-0.2.2.dist-info/entry_points.txt
oduit-0.2.2.dist-info/top_level.txt
oduit-0.2.2.dist-info/RECORD
