Metadata-Version: 2.4
Name: oduit
Version: 0.2.2
Summary: Library for controlling odoo-bin for run, update, install and test modules
Author: The oduit Authors
License: Mozilla Public License Version 2.0
Project-URL: Homepage, https://github.com/oduit/oduit
Project-URL: Documentation, https://oduit.readthedocs.io/en/stable
Project-URL: Repository, https://github.com/oduit/oduit
Project-URL: Issues, https://github.com/oduit/oduit/issues
Project-URL: Changelog, https://oduit.readthedocs.io/en/stable/changelog.html
Classifier: Development Status :: 4 - Beta
Classifier: Environment :: Console
Classifier: Intended Audience :: Developers
Classifier: License :: OSI Approved :: MIT License
Classifier: Operating System :: POSIX :: Linux
Classifier: Operating System :: MacOS :: MacOS X
Classifier: Programming Language :: Python
Classifier: Programming Language :: Python :: 3
Classifier: Programming Language :: Python :: 3.10
Classifier: Programming Language :: Python :: 3.11
Classifier: Programming Language :: Python :: 3.12
Classifier: Programming Language :: Python :: 3.13
Classifier: Topic :: Software Development
Classifier: Topic :: Utilities
Requires-Python: >=3.10
License-File: LICENSE
License-File: AUTHORS
Requires-Dist: PyYAML>=5.4
Requires-Dist: tomli>=1.2.0; python_version < "3.11"
Requires-Dist: tomli-w>=1.0.0
Requires-Dist: typer
Requires-Dist: manifestoo-core>=1.5
Dynamic: license-file
